braveblock-0.5.1.dist-info/METADATA
braveblock-0.5.1.dist-info/WHEEL
braveblock/braveblock.pyi
braveblock/__init__.py
braveblock/easylist.txt.gz
braveblock/easyprivacy.txt.gz
braveblock/braveblock.cpython-37m-darwin.so
braveblock-0.5.1.dist-info/RECORD
