Metadata-Version: 2.1
Name: braveblock
Version: 0.5.1
Summary: A fast and easy adblockplus parser and matcher based on adblock-rust package
Keywords: adblock,ads,adblocker,rust,brave,abp,pyo3
Home-Page: https://github.com/intsights/braveblock
Author: Gal Ben David <gal@intsights.com>
Author-email: Gal Ben David <gal@intsights.com>
License: MIT
Project-URL: Source Code, https://github.com/intsights/braveblock
